README.md
setup.py
BananaPY.egg-info/PKG-INFO
BananaPY.egg-info/SOURCES.txt
BananaPY.egg-info/dependency_links.txt
BananaPY.egg-info/requires.txt
BananaPY.egg-info/top_level.txt
bananapy/Client.py
bananapy/__init__.py