Metadata-Version: 1.0
Name: BananaPY
Version: 1.0.0
Summary: BananaPY - BananAPI Lib for Python
Home-page: https://github.com/bananaboy21/bananapy
Author: dat banana boi
Author-email: kang.eric.hi@gmail.com
License: MIT
Platform: UNKNOWN
